{"headers":["KlimaCube",""],"links":{"de-DE":"https://www.wolfsburg.de/digital/smart-city/klimacube"},"keywords":[],"blocks":[{"breadcrumbs":["Kontakt"],"content":"Stadt WolfsburgReferat Digitalisierung und Wirtschaft"},{"content":"Porschestraße 32 38440 Wolfsburg","breadcrumbs":["Kontakt"]},{"content":"Telefon: 05361 28-1234smart.city@stadt.wolfsburg.de","breadcrumbs":["Kontakt"]},{"content":"Der KlimaCube ist eine Sensorbox, die von der Stadt Wolfsburg entwickelt wurde, um verschiedene Umweltparameter wie Temperatur, Luftfeuchtigkeit, Feinstaubbelastung oder Lärm in Echtzeit zu messen. Damit kann die Stadt Wolfsburg ihre Daten im Bereich Klima und Umwelt erweitern. Als wichtiger Bestandteil des Projekts „Resilientes Wolfsburg“, soll der KlimaCube dabei helfen, Klimamaßnahmen datenbasiert zu entwickeln und ihren Erfolg zu messen. Dadurch können aktuelle Zustände und Veränderungen der städtischen Umwelt dargestellt und analysiert werden."},{"content":"In einem gemeinsamen Pilotprojekt mit dem Ordnungsamt analysieren wir mit dem KlimaCube die Auswirkungen einer temporären Geschwindigkeitsreduktion von Tempo 50 auf Tempo 30 auf die Lärmbelastung im Ortsteil Kästorf. Aus diesen Erkenntnissen können konkrete Maßnahmen zum Lärmschutz für die Bevölkerung vor Ort abgeleitet werden."},{"content":"Stadt WolfsburgReferat Digitalisierung und Wirtschaft"},{"content":"Porschestraße 32 38440 Wolfsburg"},{"content":"Telefon: 05361 28-1234smart.city@stadt.wolfsburg.de"},{"content":"Copyright 2025 Wolfsburg"}]}
