{"links":{"de-DE":"https://www.wolfsburg.de/kultur/kunst/kunstszene","en":"https://www.wolfsburg.de/en/kultur/kunst/kunstszene","x-default":"https://www.wolfsburg.de/en/kultur/kunst/kunstszene"},"keywords":["Kunstszene","Künstler"],"blocks":[{"content":"Sie sind Kulturschaffende*r in Wolfsburg und wünschen eine Verlinkung auf Ihre Internetseite? Dann kontaktieren Sie uns gerne:"},{"content":"Kulturwerk im M2K Telefon: 05361 28-1574 E-Mail: heike.fischer@stadt.wolfsburg.de"},{"content":"Hella Ness - Seidenkunst"},{"content":"Claudia Mucha - Malerei"},{"content":"Anette Knipphals - Ölmalerei & Zeichnungen"},{"content":"Copyright 2025 Wolfsburg"}],"headers":["Kunstszene",""]}
